Workbook

Sheet Presupuesto por Entregable
A1: Presupuesto por Entregable de la EDT — DSC PUCP Workshops
A3: Tabla 1: Tarifas por recurso humano
A4: Sigla | B4: Recurso (según el cronograma) | C4: Tarifa por hora (S/) | D4: Modalidad | J4: Nota
A5: PAT | B5: Patrocinador (L. Flores) | C5: 0 | D5: Voluntario (sin remuneración)
A6: GP | B6: Gerente de Proyecto (L. Alvites) | C6: 0 | D6: Voluntario (sin remuneración)
A7: EQ5 | B7: Equipo 5 (Planificación) | C7: 0 | D7: Voluntario (sin remuneración)
A8: DIR | B8: Directores de área (reuniones conjuntas) | C8: 0 | D8: Voluntario (sin remuneración)
A9: LOG | B9: Logística y Eventos (F. Caceres) | C9: 0 | D9: Voluntario (sin remuneración)
A10: MKT | B10: Marketing y Comunidad (A. Quispe) | C10: 0 | D10: Voluntario (sin remuneración)
A11: REX | B11: Relaciones Exteriores (S. Cruz) | C11: 0 | D11: Voluntario (sin remuneración)
A12: FIN | B12: Finanzas y Legalidad (E. Chachayma) | C12: 0 | D12: Voluntario (sin remuneración)
A13: RH | B13: RR.HH. (M. Colala) | C13: 0 | D13: Voluntario (sin remuneración)
A14: SW | B14: Desarrollo de Software (R. Chang) | C14: 0 | D14: Voluntario (sin remuneración)
A15: INF | B15: Infraestructura y Ciberseguridad (R. Sanchez) | C15: 0 | D15: Voluntario (sin remuneración)
A16: STF | B16: Voluntarios DSC | C16: 0 | D16: Voluntario (sin remuneración)
... A20: PAB | B20: Pabellón V (P. Corrado, F. Solari) | C20: 0 | D20: Cedido por la PUCP
A22: Tabla 2: Presupuesto por entregable
A23: Código EDT | B23: Entregable / recurso | C23: Cuenta de control | D23: Cantidad | E23: Tarifa (S/) | F23: Tiempo | G23: Unidad | H23: Subtotal (S/) | I23: Tipo de recurso | J23: Base de estimación / supuesto
A24: 1 | B24: INICIO
A25: 1.1 | B25: Acta de constitución del proyecto (1 día: 14/09/26 – 14/09/26) | H25: =SUM(H26:H27) -> 0 | J25: Actividades: 1.1.1
B26: Patrocinador (L. Flores) | C26: 1 | D26: 1 | E26: =$C$5 -> 0 | F26: 2 | G26: horas c/u | H26: =D26*E26*F26 -> 0 | I26: Personal
B27: Gerente de Proyecto (L. Alvites) | C27: 1 | D27: 1 | E27: =$C$6 -> 0 | F27: 2 | G27: horas c/u | H27: =D27*E27*F27 -> 0 | I27: Personal
A28: 1.2 | B28: Declaración preliminar del alcance (4 días: 15/09/26 – 18/09/26) | H28: =SUM(H29:H31) -> 0 | J28: Actividades: 1.2.1, 1.2.2
B29: Patrocinador (L. Flores) | C29: 1 | D29: 1 | E29: =$C$5 -> 0 | F29: 2 | G29: horas c/u | H29: =D29*E29*F29 -> 0 | I29: Personal
B30: Gerente de Proyecto (L. Alvites) | C30: 1 | D30: 1 | E30: =$C$6 -> 0 | F30: 2 | G30: horas c/u | H30: =D30*E30*F30 -> 0 | I30: Personal
B31: Equipo 5 (Planificación) | C31: 1 | D31: 5 | E31: =$C$7 -> 0 | F31: 6 | G31: horas c/u | H31: =D31*E31*F31 -> 0 | I31: Personal
A32: 1.3 | B32: Acuerdos iniciales con patrocinadores (22 días: 22/09/26 – 17/10/26) | H32: =SUM(H33:H34) -> 0 | J32: Actividades: 1.3.1, 1.3.2, 1.3.3
B33: Gerente de Proyecto (L. Alvites) | C33: 1 | D33: 1 | E33: =$C$6 -> 0 | F33: 24 | G33: horas c/u | H33: =D33*E33*F33 -> 0 | I33: Personal
B34: Relaciones Exteriores (S. Cruz) | C34: 1 | D34: 1 | E34: =$C$11 -> 0 | F34: 56 | G34: horas c/u | H34: =D34*E34*F34 -> 0 | I34: Personal
A35: 1.4 | B35: Registro de interesados (6 días: 15/09/26 – 21/09/26) | H35: =SUM(H36:H38) -> 0 | J35: Actividades: 1.4.1, 1.4.2
B36: Gerente de Proyecto (L. Alvites) | C36: 1 | D36: 1 | E36: =$C$6 -> 0 | F36: 2 | G36: horas c/u | H36: =D36*E36*F36 -> 0 | I36: Personal
B37: Equipo 5 (Planificación) | C37: 1 | D37: 5 | E37: =$C$7 -> 0 | F37: 10 | G37: horas c/u | H37: =D37*E37*F37 -> 0 | I37: Personal
B38: Directores de área (reuniones conjuntas) | C38: 1 | D38: 7 | E38: =$C$8 -> 0 | F38: 2 | G38: horas c/u | H38: =D38*E38*F38 -> 0 | I38: Personal
G39: Total 1. Inicio | H39: =H25+H28+H32+H35 -> 0
A40: 2 | B40: PLANIFICACIÓN
A41: 2.1 | B41: Plan de Gestión del Proyecto (12 días: 17/10/26 – 30/10/26) | H41: =SUM(H42:H45) -> 0 | J41: Actividades: 2.1.1, 2.1.2, 2.1.3
B42: Patrocinador (L. Flores) | C42: 2 | D42: 1 | E42: =$C$5 -> 0 | F42: 2 | G42: horas c/u | H42: =D42*E42*F42 -> 0 | I42: Personal
B43: Gerente de Proyecto (L. Alvites) | C43: 2 | D43: 1 | E43: =$C$6 -> 0 | F43: 18 | G43: horas c/u | H43: =D43*E43*F43 -> 0 | I43: Personal
B44: Equipo 5 (Planificación) | C44: 2 | D44: 5 | E44: =$C$7 -> 0 | F44: 10 | G44: horas c/u | H44: =D44*E44*F44 -> 0 | I44: Personal
B45: Directores de área (reuniones conjuntas) | C45: 2 | D45: 7 | E45: =$C$8 -> 0 | F45: 6 | G45: horas c/u | H45: =D45*E45*F45 -> 0 | I45: Personal
A46: 2.2 | B46: Plan de Gestión del Cronograma (12 días: 22/09/26 – 05/10/26) | H46: =SUM(H47:H50) -> 0 | J46: Actividades: 2.2.1, 2.2.2, 2.2.3
B47: Equipo 5 (Planificación) | C47: 2 | D47: 5 | E47: =$C$7 -> 0 | F47: 18 | G47: horas c/u | H47: =D47*E47*F47 -> 0 | I47: Personal
B48: Directores de área (reuniones conjuntas) | C48: 2 | D48: 7 | E48: =$C$8 -> 0 | F48: 8 | G48: horas c/u | H48: =D48*E48*F48 -> 0 | I48: Personal
B49: Logística y Eventos (F. Caceres) | C49: 2 | D49: 1 | E49: =$C$9 -> 0 | F49: 6 | G49: horas c/u | H49: =D49*E49*F49 -> 0 | I49: Personal
B50: Finanzas y Legalidad (E. Chachayma) | C50: 2 | D50: 1 | E50: =$C$12 -> 0 | F50: 6 | G50: horas c/u | H50: =D50*E50*F50 -> 0 | I50: Personal
A51: 2.3 | B51: Plan de Contenidos de los Talleres y Hackathons (Calidad) (10 días: 02/10/26 – 14/10/26) | H51: =SUM(H52:H54) -> 0 | J51: Actividades: 2.3.1, 2.3.2
B52: Gerente de Proyecto (L. Alvites) | C52: 2 | D52: 1 | E52: =$C$6 -> 0 | F52: 12 | G52: horas c/u | H52: =D52*E52*F52 -> 0 | I52: Personal
B53: Equipo 5 (Planificación) | C53: 2 | D53: 5 | E53: =$C$7 -> 0 | F53: 20 | G53: horas c/u | H53: =D53*E53*F53 -> 0 | I53: Personal
B54: RR.HH. (M. Colala) | C54: 2 | D54: 1 | E54: =$C$13 -> 0 | F54: 8 | G54: horas c/u | H54: =D54*E54*F54 -> 0 | I54: Personal
A55: 2.4 | B55: Plan de Gestión de la Publicidad y Comunicaciones (7 días: 02/10/26 – 10/10/26) | H55: =SUM(H56:H57) -> 0 | J55: Actividades: 2.4.1, 2.4.2
B56: Gerente de Proyecto (L. Alvites) | C56: 2 | D56: 1 | E56: =$C$6 -> 0 | F56: 6 | G56: horas c/u | H56: =D56*E56*F56 -> 0 | I56: Personal
B57: Marketing y Comunidad (A. Quispe) | C57: 2 | D57: 1 | E57: =$C$10 -> 0 | F57: 14 | G57: horas c/u | H57: =D57*E57*F57 -> 0 | I57: Personal
A58: 2.5 | B58: Plan de Gestión del Alcance (18 días: 15/09/26 – 05/10/26) | H58: =SUM(H59) -> 0 | J58: Actividades: 2.5.1, 2.5.2
B59: Equipo 5 (Planificación) | C59: 2 | D59: 5 | E59: =$C$7 -> 0 | F59: 16 | G59: horas c/u | H59: =D59*E59*F59 -> 0 | I59: Personal
A60: 2.6 | B60: Plan de Gestión de los Costos (12 días: 02/10/26 – 16/10/26) | H60: =SUM(H61:H62) -> 0 | J60: Actividades: 2.6.1, 2.6.2
B61: Logística y Eventos (F. Caceres) | C61: 2 | D61: 1 | E61: =$C$9 -> 0 | F61: 16 | G61: horas c/u | H61: =D61*E61*F61 -> 0 | I61: Personal
B62: Finanzas y Legalidad (E. Chachayma) | C62: 2 | D62: 1 | E62: =$C$12 -> 0 | F62: 24 | G62: horas c/u | H62: =D62*E62*F62 -> 0 | I62: Personal
A63: 2.7 | B63: Plan de Gestión de los Recursos (8 días: 02/10/26 – 12/10/26) | H63: =SUM(H64:H65) -> 0 | J63: Actividades: 2.7.1, 2.7.2
B64: Gerente de Proyecto (L. Alvites) | C64: 2 | D64: 1 | E64: =$C$6 -> 0 | F64: 8 | G64: horas c/u | H64: =D64*E64*F64 -> 0 | I64: Personal
B65: RR.HH. (M. Colala) | C65: 2 | D65: 1 | E65: =$C$13 -> 0 | F65: 16 | G65: horas c/u | H65: =D65*E65*F65 -> 0 | I65: Personal
A66: 2.8 | B66: Plan de Gestión de los Riesgos (11 días: 02/10/26 – 15/10/26) | H66: =SUM(H67:H69) -> 0 | J66: Actividades: 2.8.1, 2.8.2
B67: Gerente de Proyecto (L. Alvites) | C67: 2 | D67: 1 | E67: =$C$6 -> 0 | F67: 14 | G67: horas c/u | H67: =D67*E67*F67 -> 0 | I67: Personal
B68: Equipo 5 (Planificación) | C68: 2 | D68: 5 | E68: =$C$7 -> 0 | F68: 8 | G68: horas c/u | H68: =D68*E68*F68 -> 0 | I68: Personal
B69: Finanzas y Legalidad (E. Chachayma) | C69: 2 | D69: 1 | E69: =$C$12 -> 0 | F69: 6 | G69: horas c/u | H69: =D69*E69*F69 -> 0 | I69: Personal
A70: 2.9 | B70: Plan de Gestión de las Adquisiciones (sponsors y merchandising) (11 días: 02/10/26 – 15/10/26) | H70: =SUM(H71:H72) -> 0 | J70: Actividades: 2.9.1, 2.9.2
B71: Relaciones Exteriores (S. Cruz) | C71: 2 | D71: 1 | E71: =$C$11 -> 0 | F71: 10 | G71: horas c/u | H71: =D71*E71*F71 -> 0 | I71: Personal
B72: Finanzas y Legalidad (E. Chachayma) | C72: 2 | D72: 1 | E72: =$C$12 -> 0 | F72: 16 | G72: horas c/u | H72: =D72*E72*F72 -> 0 | I72: Personal
G73: Total 2. Planificación | H73: =H41+H46+H51+H55+H58+H60+H63+H66+H70 -> 0
A74: 3 | B74: EJECUCIÓN
A75: 3.1 | B75: Patrocinios y adquisiciones — cuenta de control (199 días: 31/10/26 – 30/06/27) | H75: =H76+H82+H86 -> 1490
A76: 3.1.1 | B76: Expediente de patrocinios gestionados (199 días: 31/10/26 – 30/06/27) | H76: =SUM(H77:H81) -> 0 | J76: Actividades: 3.1.1.1, 3.1.1.2, 3.1.1.3, 3.1.1.4, 3.1.1.5, 3.1.1.6, 3.1.1.7
B77: Patrocinador (L. Flores) | C77: 3.1 | D77: 1 | E77: =$C$5 -> 0 | F77: 2 | G77: horas c/u | H77: =D77*E77*F77 -> 0 | I77: Personal
B78: Gerente de Proyecto (L. Alvites) | C78: 3.1 | D78: 1 | E78: =$C$6 -> 0 | F78: 2 | G78: horas c/u | H78: =D78*E78*F78 -> 0 | I78: Personal
B79: Marketing y Comunidad (A. Quispe) | C79: 3.1 | D79: 1 | E79: =$C$10 -> 0 | F79: 10 | G79: horas c/u | H79: =D79*E79*F79 -> 0 | I79: Personal
B80: Relaciones Exteriores (S. Cruz) | C80: 3.1 | D80: 1 | E80: =$C$11 -> 0 | F80: 154 | G80: horas c/u | H80: =D80*E80*F80 -> 0 | I80: Personal | J80: Negociación: 2 h/día (RR.EE.) y 0.5 h/día (Finanzas).
B81: Finanzas y Legalidad (E. Chachayma) | C81: 3.1 | D81: 1 | E81: =$C$12 -> 0 | F81: 82 | G81: horas c/u | H81: =D81*E81*F81 -> 0 | I81: Personal | J81: Negociación: 2 h/día (RR.EE.) y 0.5 h/día (Finanzas). Seguimiento de desembolsos: 1 h por semana.
A82: 3.1.2 | B82: Diseño de merchandising (8 días: 23/01/27 – 01/02/27) | H82: =SUM(H83:H85) -> 0 | J82: Actividades: 3.1.2.1, 3.1.2.2
B83: Gerente de Proyecto (L. Alvites) | C83: 3.1 | D83: 1 | E83: =$C$6 -> 0 | F83: 4 | G83: horas c/u | H83: =D83*E83*F83 -> 0 | I83: Personal
B84: Marketing y Comunidad (A. Quispe) | C84: 3.1 | D84: 1 | E84: =$C$10 -> 0 | F84: 12 | G84: horas c/u | H84: =D84*E84*F84 -> 0 | I84: Personal
B85: Finanzas y Legalidad (E. Chachayma) | C85: 3.1 | D85: 1 | E85: =$C$12 -> 0 | F85: 4 | G85: horas c/u | H85: =D85*E85*F85 -> 0 | I85: Personal
A86: 3.1.3 | B86: Orden de compra y acta de recepción de merchandising (15 días: 02/02/27 – 18/02/27) | H86: =SUM(H87:H91) -> 1490 | J86: Actividades: 3.1.3.1, 3.1.3.2, 3.1.3.3
B87: Logística y Eventos (F. Caceres) | C87: 3.1 | D87: 1 | E87: =$C$9 -> 0 | F87: 2 | G87: horas c/u | H87: =D87*E87*F87 -> 0 | I87: Personal
B88: Finanzas y Legalidad (E. Chachayma) | C88: 3.1 | D88: 1 | E88: =$C$12 -> 0 | F88: 9 | G88: horas c/u | H88: =D88*E88*F88 -> 0 | I88: Personal
B89: Polos para el staff voluntario | C89: 3.1 | D89: 30 | E89: 25 | F89: 1 | G89: compra única | H89: =D89*E89*F89 -> 750 | I89: Materiales | J89: Cantidad = staff voluntario supuesto.
B90: Stickers del programa | C90: 3.1 | D90: 400 | E90: 0.5 | F90: 1 | G90: compra única | H90: =D90*E90*F90 -> 200 | I90: Materiales | J90: Se reparten en los 7 eventos.
B91: Tomatodos | C91: 3.1 | D91: 45 | E91: 12 | F91: 1 | G91: compra única | H91: =D91*E91*F91 -> 540 | I91: Materiales | J91: Artículo del 3.1.2.1. Supuesto: obsequio a los expertos; destino y precio por confirmar.
A92: 3.2 | B92: Publicidad y difusión — cuenta de control (220 días: 07/11/26 – 04/08/27) | H92: =H93+H101 -> 1050
A93: 3.2.1 | B93: Piezas gráficas y audiovisuales (220 días: 07/11/26 – 04/08/27) | H93: =SUM(H94:H100) -> 1050 | J93: Actividades: 3.2.1.1, 3.2.1.2, 3.2.1.3, 3.2.1.4, 3.2.1.5, 3.2.1.6
B94: Marketing y Comunidad (A. Quispe) | C94: 3.2 | D94: 1 | E94: =$C$10 -> 0 | F94: 172 | G94: horas c/u | H94: =D94*E94*F94 -> 0 | I94: Personal | J94: Producción continua de piezas: 1 h/día.
B95: Desarrollo de Software (R. Chang) | C95: 3.2 | D95: 1 | E95: =$C$14 -> 0 | F95: 54 | G95: horas c/u | H95: =D95*E95*F95 -> 0 | I95: Personal
B96: Infraestructura y Ciberseguridad (R. Sanchez) | C96: 3.2 | D96: 1 | E96: =$C$15 -> 0 | F96: 14 | G96: horas c/u | H96: =D96*E96*F96 -> 0 | I96: Personal
B97: Dominio de la web oficial | C97: 3.2 | D97: 1 | E97: 60 | F97: 1 | G97: año | H97: =D97*E97*F97 -> 60 | I97: Tecnología | J97: Se compra al iniciar 3.2.1.2 (04/01/27). Hosting con créditos GCP (S/ 0).
B98: Banners roll-up | C98: 3.2 | D98: 2 | E98: 180 | F98: 1 | G98: compra única | H98: =D98*E98*F98 -> 360 | I98: Materiales | J98: Para el lanzamiento (3.2.1.5, 15/02/27).
B99: Afiches impresos para el campus | C99: 3.2 | D99: 100 | E99: 1.5 | F99: 1 | G99: compra única | H99: =D99*E99*F99 -> 150 | I99: Materiales | J99: Tamaño A3; lanzamiento.
B100: Publicidad pagada en Instagram y LinkedIn | C100: 3.2 | D100: 1 | E100: 80 | F100: 6 | G100: meses | H100: =D100*E100*F100 -> 480 | I100: Servicios | J100: Durante 3.2.1.6 (16/02 – 04/08/27).
A101: 3.2.2 | B101: Informes de campañas publicitarias (104 días: 29/03/27 – 03/08/27) | H101: =SUM(H102) -> 0 | J101: Actividades: 3.2.2.1, 3.2.2.2, 3.2.2.3, 3.2.2.4, 3.2.2.5
B102: Marketing y Comunidad (A. Quispe) | C102: 3.2 | D102: 1 | E102: =$C$10 -> 0 | F102: 20 | G102: horas c/u | H102: =D102*E102*F102 -> 0 | I102: Personal
A103: 3.3 | B103: Primera Ronda de Talleres – Módulo I "Hack With DSC" (Pabellón V) — cuenta de control (110 días: 16/11/26 – 30/03/27) | H103: =H104+H109+H115+H117+H120+H125 -> 560
A104: 3.3.1 | B104: Equipo de voluntarios del evento (21 días: 04/02/27 – 27/02/27) | H104: =SUM(H105:H108) -> 0 | J104: Actividades: 3.3.1.1.1, 3.3.1.2.1, 3.3.1.3.1
B105: Logística y Eventos (F. Caceres) | C105: 3.3 | D105: 1 | E105: =$C$9 -> 0 | F105: 4 | G105: horas c/u | H105: =D105*E105*F105 -> 0 | I105: Personal
...

Sheet Flujo de Caja
A1: Flujo de Caja — enero a agosto 2027
A2: Solo desembolsos monetarios, ubicados en el mes en que el cronograma detallado programa la compra o el evento. Los auspicios entran en tramos al menos 30 días antes de los eventos que financian (R2).
A4: Concepto | B4: Mes 1 Ene-27 | C4: Mes 2 Feb-27 | D4: Mes 3 Mar-27 | E4: Mes 4 Abr-27 | F4: Mes 5 May-27 | G4: Mes 6 Jun-27 | H4: Mes 7 Jul-27 | I4: Mes 8 Ago-27 | J4: Total | L4: Tramo de auspicios | M4: % de la meta | N4: Fecha límite de desembolso
A5: Ingresos (*) | L5: Tramo 1 (febrero) | M5: 0.3 | N5: Antes del 02/02 — orden de compra del merchandising (3.1.3.1) y 30 días antes del Módulo I
A6: Capital semilla DSC PUCP | B6: ='Presupuesto por Entregable'!H457 -> 300 | J6: =SUM(B6:I6) -> 300 | L6: Tramo 2 (abril) | M6: 0.2 | N6: Antes del 29/04 — 30 días antes del Torneo de Vibecoding
A7: Auspicios — tramo 1 (30 %) | C7: ='Presupuesto por Entregable'!$H$458*$M$5 -> 5460 | J7: =SUM(B7:I7) -> 5460 | L7: Tramo 3 (junio) | M7: 0.5 | N7: Antes del 30/06 — 30 días antes de la hackathon de 24 h
A8: Auspicios — tramo 2 (20 %) | E8: ='Presupuesto por Entregable'!$H$458*$M$6 -> 3640 | J8: =SUM(B8:I8) -> 3640 | L8: Total | M8: =SUM(M5:M7) -> 1
A9: Auspicios — tramo 3 (50 %) | G9: ='Presupuesto por Entregable'!$H$458*$M$7 -> 9100 | J9: =SUM(B9:I9) -> 9100
A10: Total Ingresos | B10: =SUM(B6:B9) -> 300 | C10: =SUM(C6:C9) -> 5460 | D10: =SUM(D6:D9) -> 0 | E10: =SUM(E6:E9) -> 3640 | F10: =SUM(F6:F9) -> 0 | G10: =SUM(G6:G9) -> 9100 | H10: =SUM(H6:H9) -> 0 | I10: =SUM(I6:I9) -> 0 | J10: =SUM(B10:I10) -> 18500
A11: Egresos
A12: 3.1 Patrocinios y adquisiciones (merchandising) | C12: ='Presupuesto por Entregable'!H414 -> 1490 | J12: =SUM(B12:I12) -> 1490
A13: 3.2 Publicidad y difusión | B13: ='Presupuesto por Entregable'!H97 -> 60 | C13: ='Presupuesto por Entregable'!H98+'Presupuesto por Entregable'!H99+'Presupuesto por Entregable'!H100/'Presupuesto por Entregable'!F100 -> 590 | D13: ='Presupuesto por Entregable'!H100/'Presupuesto por Entregable'!F100 -> 80 | E13: ='Presupuesto por Entregable'!H100/'Presupuesto por Entregable'!F100 -> 80 | F13: ='Presupuesto por Entregable'!H100/'Presupuesto por Entregable'!F100 -> 80 | G13: ='Presupuesto por Entregable'!H100/'Presupuesto por Entregable'!F100 -> 80 | H13: ='Presupuesto por Entregable'!H100/'Presupuesto por Entregable'!F100 -> 80 | J13: =SUM(B13:I13) -> 1050
A14: 3.3 Primera Ronda de Talleres — Módulo I | D14: ='Presupuesto por Entregable'!H416 -> 560 | J14: =SUM(B14:I14) -> 560
A15: 3.6 Hackathon "Kachimbo" | D15: ='Presupuesto por Entregable'!H419 -> 500 | J15: =SUM(B15:I15) -> 500
A16: 3.4 Segunda Ronda de Talleres — Módulo II | E16: ='Presupuesto por Entregable'!H417 -> 560 | J16: =SUM(B16:I16) -> 560
A17: 3.7 Competencia de Kaggle | E17: ='Presupuesto por Entregable'!H420 -> 500 | J17: =SUM(B17:I17) -> 500
A18: 3.8 Torneo de Vibecoding (8 h) | F18: ='Presupuesto por Entregable'!H421 -> 2290 | J18: =SUM(B18:I18) -> 2290
A19: 3.5 Tercera Ronda de Talleres — Módulo III y premiación GCP | G19: ='Presupuesto por Entregable'!H418 -> 980 | J19: =SUM(B19:I19) -> 980
A20: 3.9 Hackathon Internacional de 24 h | H20: ='Presupuesto por Entregable'!H422 -> 6590 | J20: =SUM(B20:I20) -> 6590
A21: Total Egresos | B21: =SUM(B12:B20) -> 60 | C21: =SUM(C12:C20) -> 2080 | D21: =SUM(D12:D20) -> 1140 | E21: =SUM(E12:E20) -> 1140 | F21: =SUM(F12:F20) -> 2370 | G21: =SUM(G12:G20) -> 1060 | H21: =SUM(H12:H20) -> 6670 | I21: =SUM(I12:I20) -> 0 | J21: =SUM(B21:I21) -> 14520
A22: Saldo del mes (ingresos − egresos) | B22: =B10-B21 -> 240 | C22: =C10-C21 -> 3380 | D22: =D10-D21 -> -1140 | E22: =E10-E21 -> 2500 | F22: =F10-F21 -> -2370 | G22: =G10-G21 -> 8040 | H22: =H10-H21 -> -6670 | I22: =I10-I21 -> 0 | J22: =SUM(B22:I22) -> 3980
A23: Total Acumulado | B23: =B10-B21 -> 240 | C23: =B23+C10-C21 -> 3620 | D23: =C23+D10-D21 -> 2480 | E23: =D23+E10-E21 -> 4980 | F23: =E23+F10-F21 -> 2610 | G23: =F23+G10-G21 -> 10650 | H23: =G23+H10-H21 -> 3980 | I23: =H23+I10-I21 -> 3980
A25: Comprobación: saldo final esperado = superávit + contingencia + gestión | B25: ='Presupuesto por Entregable'!H460+'Presupuesto por Entregable'!H448+'Presupuesto por Entregable'!H450 -> 3980
A26: Diferencia con el acumulado de agosto (debe ser 0) | B26: =I23-B25 -> 0
A27: Saldo mínimo del periodo (no debe ser negativo) | B27: =MIN(B23:I23) -> 240
A29: * Los ingresos provienen del capital semilla de DSC PUCP y de los auspicios corporativos (P11: los participantes no pagan inscripción).
A30: * Los egresos corresponden a las cuentas de control de la hoja 'Presupuesto por Entregable'; las reservas no se programan porque solo se usan si ocurre el riesgo o el imprevisto.
A31: * En enero solo se gasta el dominio web, dentro del tope de S/ 300 del capital semilla. Ninguna compra se compromete antes del primer desembolso (R2).
A32: * En un entorno ideal, el total acumulado de agosto es igual al superávit más las reservas no utilizadas.

Sheet Curva S
A1: Curva S — costo planificado acumulado vs. línea base y financiamiento
A2: Se grafica contra la línea base de costos, no contra la reserva de gestión (sesión 7).
A4: Mes | B4: Costo planificado del mes | C4: Costo acumulado | D4: Línea base de costos | E4: Financiamiento acumulado
A5: Ene-27 | B5: ='Flujo de Caja'!B21 -> 60 | C5: =B5 -> 60 | D5: ='Presupuesto por Entregable'!$H$449 -> 15680 | E5: ='Flujo de Caja'!B10 -> 300
A6: Feb-27 | B6: ='Flujo de Caja'!C21 -> 2080 | C6: =C5+B6 -> 2140 | D6: ='Presupuesto por Entregable'!$H$449 -> 15680 | E6: =E5+'Flujo de Caja'!C10 -> 5760
A7: Mar-27 | B7: ='Flujo de Caja'!D21 -> 1140 | C7: =C6+B7 -> 3280 | D7: ='Presupuesto por Entregable'!$H$449 -> 15680 | E7: =E6+'Flujo de Caja'!D10 -> 5760
A8: Abr-27 | B8: ='Flujo de Caja'!E21 -> 1140 | C8: =C7+B8 -> 4420 | D8: ='Presupuesto por Entregable'!$H$449 -> 15680 | E8: =E7+'Flujo de Caja'!E10 -> 9400
A9: May-27 | B9: ='Flujo de Caja'!F21 -> 2370 | C9: =C8+B9 -> 6790 | D9: ='Presupuesto por Entregable'!$H$449 -> 15680 | E9: =E8+'Flujo de Caja'!F10 -> 9400
A10: Jun-27 | B10: ='Flujo de Caja'!G21 -> 1060 | C10: =C9+B10 -> 7850 | D10: ='Presupuesto por Entregable'!$H$449 -> 15680 | E10: =E9+'Flujo de Caja'!G10 -> 18500
A11: Jul-27 | B11: ='Flujo de Caja'!H21 -> 6670 | C11: =C10+B11 -> 14520 | D11: ='Presupuesto por Entregable'!$H$449 -> 15680 | E11: =E10+'Flujo de Caja'!H10 -> 18500
A12: Ago-27 | B12: ='Flujo de Caja'!I21 -> 0 | C12: =C11+B12 -> 14520 | D12: ='Presupuesto por Entregable'!$H$449 -> 15680 | E12: =E11+'Flujo de Caja'!I10 -> 18500
